setup.py
dsnd_dist_AG/Binomialdistribution.py
dsnd_dist_AG/Gaussiandistribution.py
dsnd_dist_AG/Generaldistribution.py
dsnd_dist_AG/__init__.py
dsnd_dist_AG.egg-info/PKG-INFO
dsnd_dist_AG.egg-info/SOURCES.txt
dsnd_dist_AG.egg-info/dependency_links.txt
dsnd_dist_AG.egg-info/not-zip-safe
dsnd_dist_AG.egg-info/top_level.txt